overwatch/__init__.py
overwatch/stats/__init__.py
overwatch/stats/extractors.py
overwatch/stats/ids.py
overwatch/stats/parsers.py
overwatch/stats/utils.py
overwatch_stats-1.1.3.dist-info/METADATA
overwatch_stats-1.1.3.dist-info/RECORD
overwatch_stats-1.1.3.dist-info/WHEEL
overwatch_stats-1.1.3.dist-info/top_level.txt
