Metadata-Version: 2.1
Name: overwatch-stats
Version: 1.1.3
Summary: A library to query a player's overwatch stats from Battle.net
Home-page: https://github.com/jonghwanhyeon/overwatch-stats
Author: Jonghwan Hyeon
Author-email: hyeon0145@gmail.com
License: MIT
Keywords: overwatch stats
Platform: UNKNOWN
Classifier: Development Status :: 4 - Beta
Classifier: Intended Audience :: Developers
Classifier: License :: OSI Approved :: MIT License
Classifier: Topic :: Games/Entertainment :: First Person Shooters
Classifier: Programming Language :: Python :: 3
Classifier: Programming Language :: Python :: 3.3
Classifier: Programming Language :: Python :: 3.4
Classifier: Programming Language :: Python :: 3.5
Classifier: Programming Language :: Python :: 3.6
Classifier: Programming Language :: Python :: 3 :: Only
Requires-Dist: requests
Requires-Dist: lxml
Requires-Dist: inflect
